Metadata-Version: 2.1
Name: dycGroup
Version: 1.0.0.0
Summary: ${Description}
Author: dyc
Author-email: your@email.com
